platinum/__init__.py
platinum/chromium.py
platinum/console.py
platinum/constants.py
platinum/exceptions.py
platinum/user_agent.py
platinum/data/android_build.json
platinum/data/android_dev.json
platinum/data/ios.json
platinum/data/opera_build.json
platinum-1.5.0.dist-info/LICENSE
platinum-1.5.0.dist-info/METADATA
platinum-1.5.0.dist-info/WHEEL
platinum-1.5.0.dist-info/entry_points.txt
platinum-1.5.0.dist-info/top_level.txt
platinum-1.5.0.dist-info/RECORD
