Metadata-Version: 2.1
Name: platinum
Version: 1.5.0
Summary: Frequently used google chrome commands mappings. A User-Agent generator. All for automation.
Home-page: https://github.com/ffujiawei/platinum
Author: White Turing
Author-email: fujiawei@stu.hznu.edu.cn
License: Apache 2.0
Keywords: chromium,automation,testing,user-agent
Platform: UNKNOWN
Classifier: Intended Audience :: Developers
Classifier: License :: OSI Approved :: Apache Software License
Classifier: Operating System :: OS Independent
Classifier: Programming Language :: Python :: 2.7
Classifier: Programming Language :: Python :: 3.3
Classifier: Programming Language :: Python :: 3.4
Classifier: Programming Language :: Python :: 3.5
Classifier: Programming Language :: Python :: 3.6
Classifier: Programming Language :: Python :: 3.7
Classifier: Programming Language :: Python :: Implementation :: CPython
Classifier: Programming Language :: Python :: Implementation :: PyPy
Classifier: Topic :: Software Development :: Testing
Classifier: Topic :: Software Development :: Libraries
Classifier: Topic :: Internet :: WWW/HTTP
Requires-Dist: six
Requires-Dist: requests-html
